cubik/moves.py
cubik/_cubik_moves.so
cubik/cubik.py
cubik/_cubik.so
cubik/__init__.py
cubik/bin/cubik_cli
cubik-0.3.3.dist-info/WHEEL
cubik-0.3.3.dist-info/METADATA
cubik-0.3.3.dist-info/RECORD
cubik-0.3.3.dist-info/licenses/LICENSE
