Metadata-Version: 2.2
Name: cubik
Version: 0.3.3
Summary: Fast Rubik's Cube engine with Python bindings
Keywords: rubik,cube,puzzle,solver
Author: Matthew Peters
License: MIT
Classifier: Programming Language :: Python :: 3
Classifier: Programming Language :: C++
Classifier: Operating System :: OS Independent
Project-URL: Homepage, https://github.com/petermatts/cubik
Requires-Python: >=3.8
